{"name":"数学","slug":"数学","count":2,"postlist":[{"title":"Latex数学公式","uid":"409671003844af96bee509bb7a2097ee","slug":"Math/Latex_formula","date":"2022-06-20T02:24:00.000Z","updated":"2022-06-30T07:32:48.143Z","comments":true,"path":"api/articles/Math/Latex_formula.json","keywords":null,"cover":null,"text":"数学公式的插入 类型 环境名称 行内公式 $...$ 独行公式 $$...$$ 希腊字母 命令 大写 小写 alpha \\(A\\) \\(\\alpha\\) gamma \\(\\Gamma\\) \\(\\gamma\\) epsilon \\(E\\) \\(\\epsilon\\) eta \\(H\\...","link":"","photos":[],"count_time":{"symbolsCount":"14k","symbolsTime":"13 mins."},"categories":[{"name":"数学","slug":"数学","count":2,"path":"api/categories/数学.json"}],"tags":[{"name":"手册","slug":"手册","count":2,"path":"api/tags/手册.json"}],"author":{"name":"爱慢跑的乌龟","slug":"blog-author","avatar":"/img/avatar1.jpg","link":"/","description":"求知若饥，虚心若愚！","socials":{"github":"https://github.com/ansonxu1998","twitter":"","stackoverflow":"","wechat":"","qq":"","weibo":"","zhihu":"","csdn":"","juejin":"","customs":{}}}},{"title":"矩阵的导数运算(1)","uid":"d97c1a68285e6aac869410b1223c6673","slug":"Math/矩阵的导数运算1","date":"2023-02-10T08:37:00.000Z","updated":"2023-04-15T02:31:18.360Z","comments":true,"path":"api/articles/Math/矩阵的导数运算1.json","keywords":null,"cover":null,"text":"矩阵的导数运算 (1) 标量方程对向量的导数： 定义： \\[ \\frac{\\partial f(\\vec{y})}{\\partial \\vec{y}}=\\begin{bmatrix}\\frac{\\partial f(\\vec{y})}{\\partial y_1}\\\\\\frac{\\...","link":"","photos":[],"count_time":{"symbolsCount":"2.7k","symbolsTime":"2 mins."},"categories":[{"name":"数学","slug":"数学","count":2,"path":"api/categories/数学.json"}],"tags":[{"name":"矩阵求导","slug":"矩阵求导","count":1,"path":"api/tags/矩阵求导.json"}],"author":{"name":"爱慢跑的乌龟","slug":"blog-author","avatar":"/img/avatar1.jpg","link":"/","description":"求知若饥，虚心若愚！","socials":{"github":"https://github.com/ansonxu1998","twitter":"","stackoverflow":"","wechat":"","qq":"","weibo":"","zhihu":"","csdn":"","juejin":"","customs":{}}}}]}